{
  "id": "1978133907145973926",
  "author": "@daniel__designs",
  "author_name": "Daniel Destefanis",
  "created_at": "2025-10-14T16:20:50.000Z",
  "text": "Glad to see people still discovering tools I made!\n\nMy new side project is soo much cooler than this though it’s unreal. Can’t wait to share more soon https://t.co/Wy7rZeCkEU",
  "urls": [],
  "conversation_id": "1978133907145973926",
  "referenced_tweets": [
    {
      "id": "1976898543396045137",
      "type": "quoted"
    }
  ],
  "included": [
    {
      "id": "1976898543396045137",
      "text": "Wft🤯 I just found usefull site for editors &amp; designers.\n\nNow you can generate unlimited free gradients for your next project all for free🔥👀.\n\nAdjust Noise, shape, colors &amp; Gradient. https://t.co/XCivKKiJhB"
    }
  ],
  "source_url": "https://x.com/daniel__designs/status/1978133907145973926"
}
