{
  "id": "2074530535561638354",
  "author": "@LiuLawrence45",
  "author_name": "Lawrence Liu",
  "created_at": "2026-07-07T16:26:37.000Z",
  "text": "this honestly terrifies me https://t.co/JOWMXDLfXo",
  "urls": [],
  "conversation_id": "2074530535561638354",
  "referenced_tweets": [
    {
      "id": "2074525110774681830",
      "type": "quoted"
    }
  ],
  "included": [
    {
      "id": "2074525110774681830",
      "text": "Introducing Willow Frontier Mini and Willow Frontier Pro.\n\nFrontier Mini gives everyone free, unlimited dictation.\n\nFrontier Pro is our most accurate model yet, built for power users and teams who want the fastest and best dictation experience. https://t.co/p5ImXqoNIf"
    }
  ],
  "source_url": "https://x.com/LiuLawrence45/status/2074530535561638354"
}
