{
  "id": "2076284369883615555",
  "author": "@argofowl",
  "author_name": "🥔🥔🥔",
  "created_at": "2026-07-12T12:35:43.000Z",
  "text": "introducing https://t.co/20es64pAqZ\n\na dictionary for ui things you can see but can't name\n\nmade it because i'm primarily a designer, and my biggest resistance was always knowing what things are called when prompting my agents\n\nit learns as people use it: every search teaches the site new words, and the built-in pocket dictionary grows with it\n\ngive it a try and let me know what you think\n\ncan't find something? dm me and i'll add it\n\ni want this to be the lowest resistance resource you have\n\nyou can just build things",
  "urls": [
    "http://namethatui.com"
  ],
  "conversation_id": "2076284369883615555",
  "referenced_tweets": [],
  "included": [],
  "source_url": "https://x.com/argofowl/status/2076284369883615555"
}
